Metadata-Version: 1.0
Name: wolfgang
Version: 0.2
Summary: A Python library for vectors.
Home-page: https://github.com/Cisplatin/wolfgang
Author: Simon Hajjar
Author-email: simon.j.hajjar@gmail.com
License: MIT
Platform: UNKNOWN
